README.md
setup.cfg
setup.py
openreview/__init__.py
openreview/const.py
openreview/main.py
openreview.egg-info/PKG-INFO
openreview.egg-info/SOURCES.txt
openreview.egg-info/dependency_links.txt
openreview.egg-info/requires.txt
openreview.egg-info/top_level.txt
test/__init__.py
test/basic.py