Metadata-Version: 2.1
Name: openreview
Version: 0.0.2
Summary: Openreview web API client
Home-page: https://github.com/theblackcat102/openreview_api_py
Author: Zhi Rui Tam
Author-email: ray@currentsapi.services
License: MIT
Keywords: openreview,data-mining,
Platform: UNKNOWN
